mcpacket/__init__.py
mcpacket/_version.py
mcpacket/cli.py
mcpacket/core/__init__.py
mcpacket/core/config.py
mcpacket/core/server.py
mcpacket/modules/__init__.py
mcpacket/modules/base.py
mcpacket/modules/dns.py
mcpacket/resources/__init__.py
mcpacket/resources/references.py
mcpacket-0.1.3.dist-info/licenses/LICENSE
mcpacket-0.1.3.dist-info/METADATA
mcpacket-0.1.3.dist-info/WHEEL
mcpacket-0.1.3.dist-info/entry_points.txt
mcpacket-0.1.3.dist-info/top_level.txt
mcpacket-0.1.3.dist-info/RECORD
