Metadata-Version: 2.4
Name: mcpacket
Version: 0.1.3
Summary: A modular Python MCP Server for analyzing PCAP files
Author: mcpacket contributors
License: MIT
Project-URL: Homepage, https://github.com/danohn/mcpacket
Project-URL: Repository, https://github.com/danohn/mcpacket
Project-URL: Issues, https://github.com/danohn/mcpacket/issues
Keywords: pcap,network,analysis,mcp,dns
Classifier: Development Status :: 3 - Alpha
Classifier: Intended Audience :: Developers
Classifier: Intended Audience :: System Administrators
Classifier: License :: OSI Approved :: MIT License
Classifier: Programming Language :: Python :: 3
Classifier: Programming Language :: Python :: 3.10
Classifier: Programming Language :: Python :: 3.11
Classifier: Programming Language :: Python :: 3.12
Classifier: Topic :: System :: Networking :: Monitoring
Classifier: Topic :: Security
Requires-Python: >=3.10
License-File: LICENSE
Requires-Dist: fastmcp
Requires-Dist: scapy
Provides-Extra: test
Requires-Dist: pytest; extra == "test"
Requires-Dist: pytest-cov; extra == "test"
Requires-Dist: setuptools-scm[toml]; extra == "test"
Provides-Extra: dev
Requires-Dist: setuptools-scm[toml]; extra == "dev"
Requires-Dist: build; extra == "dev"
Requires-Dist: twine; extra == "dev"
Requires-Dist: ruff; extra == "dev"
Provides-Extra: docs
Requires-Dist: sphinx>=7.0; extra == "docs"
Requires-Dist: sphinx-rtd-theme; extra == "docs"
Requires-Dist: myst-parser; extra == "docs"
Requires-Dist: sphinx-autodoc-typehints; extra == "docs"
Requires-Dist: sphinx-copybutton; extra == "docs"
Requires-Dist: linkify-it-py; extra == "docs"
Dynamic: license-file
